softrees-0.0.3.dist-info/WHEEL
softrees-0.0.3.dist-info/top_level.txt
softrees-0.0.3.dist-info/LICENSE
softrees-0.0.3.dist-info/RECORD
softrees-0.0.3.dist-info/METADATA
softrees/__init__.py
softrees/pytorch/soft_tree_ensemble_tensor.py
softrees/pytorch/__init__.py
softrees/pytorch/soft_tree_ensemble_layer.py
softrees/pytorch/soft_tree_ensemble_train.py
softrees/runtime/soft_oblique_tree_ensemble_cython.cpython-310-x86_64-linux-gnu.so
softrees/runtime/__init__.py
softrees/runtime/soft_oblique_tree_ensemble_numba.py
softrees/runtime/hard_oblique_tree_ensemble.py
softrees/runtime/soft_tree_ensemble.py
softrees/runtime/hard_axis_aligned_tree_ensemble.py
softrees/runtime/soft_oblique_tree_ensemble_c.cpython-310-x86_64-linux-gnu.so
softrees/runtime/soft_axis_aligned_tree_ensemble_numba.py
softrees/runtime/soft_tree_ensemble_common.py
softrees/training/greedy_hard_axis_aligned_tree_ensemble.py
softrees/training/__init__.py
softrees/training/soft_oblique_tree_ensemble_numba.py
softrees/training/greedy_soft_oblique_tree_ensemble.py
softrees/training/soft_tree_ensemble_api.py
softrees/training/soft_tree_ensemble_training.py
softrees/training/greedy_hard_oblique_tree_ensemble.py
softrees/training/soft_axis_aligned_tree_ensemble_numba.py
softrees/training/soft_tree_ensemble_common.py
