Metadata-Version: 2.1
Name: softrees
Version: 0.0.3
Summary: Module that implement a soft tree ensemble layer
Author: Martin de La Gorce
Author-email: martin.delagorce@gmail.com
License: MIT
License-File: LICENSE
Requires-Dist: numpy
Requires-Dist: numba
Requires-Dist: tqdm
Requires-Dist: torch
